<annotation><folder>PigEarTag</folder><filename>20171129_DSHJS1976817000822_6337312number4.jpg</filename><source><dataset>Pig</dataset><id>20171129_DSHJS1976817000822_6337312number4</id></source><owner><name>Deepfinch</name></owner><size><width>216</width><height>238</height><depth>3</depth></size><segmented>0</segmented><object><name>text</name><pose>Left</pose><truncated>1</truncated><difficult>0</difficult><bndbox><xmin>2</xmin><ymin>2</ymin><xmax>49</xmax><ymax>54</ymax></bndbox></object></annotation>