<annotation><folder>PigEarTag</folder><filename>20180426_DSHJT0776818000132_10539744number1.jpg</filename><source><dataset>Pig</dataset><id>20180426_DSHJT0776818000132_10539744number1</id></source><owner><name>Deepfinch</name></owner><size><width>197</width><height>220</height><depth>3</depth></size><segmented>0</segmented><object><name>text</name><pose>Left</pose><truncated>1</truncated><difficult>0</difficult><bndbox><xmin>33</xmin><ymin>41</ymin><xmax>76</xmax><ymax>89</ymax></bndbox></object></annotation>